telegram_pay/__init__.py
telegram_pay/enums.py
telegram_pay/models.py
telegram_pay-0.1.5.dist-info/LICENSE
telegram_pay-0.1.5.dist-info/METADATA
telegram_pay-0.1.5.dist-info/WHEEL
telegram_pay-0.1.5.dist-info/RECORD
