Metadata-Version: 2.1
Name: telegram-pay
Version: 0.1.5
Summary: Wrapper for api.pay.4u.studio
License: MIT
Author: Snimshchikov Ilya
Author-email: snimshchikov.ilya@gmail.com
Requires-Python: >=3.9,<4.0
Classifier: License :: OSI Approved :: MIT License
Classifier: Programming Language :: Python :: 3
Classifier: Programming Language :: Python :: 3.9
Classifier: Programming Language :: Python :: 3.10
Classifier: Programming Language :: Python :: 3.11
Requires-Dist: aiohttp (>=3.8.4,<4.0.0)
Requires-Dist: pydantic (>=2.0.0,<3.0.0)
Requires-Dist: pytz (>=2022.7.1,<2023.0.0)
